libascendc_kernels_npu.a
bitsandbytes/__init__.py
bitsandbytes/__main__.py
bitsandbytes/_version.py
bitsandbytes/cextension.py
bitsandbytes/consts.py
bitsandbytes/cuda_specs.py
bitsandbytes/functional.py
bitsandbytes/libbitsandbytes_npu.so
bitsandbytes/npu_specs.py
bitsandbytes/utils.py
bitsandbytes/autograd/__init__.py
bitsandbytes/autograd/_functions.py
bitsandbytes/backends/__init__.py
bitsandbytes/backends/base.py
bitsandbytes/backends/cpu.py
bitsandbytes/backends/cpu_xpu_common.py
bitsandbytes/backends/cuda.py
bitsandbytes/backends/mps.py
bitsandbytes/backends/npu.py
bitsandbytes/backends/rocm.py
bitsandbytes/backends/xpu.py
bitsandbytes/diagnostics/__init__.py
bitsandbytes/diagnostics/cuda.py
bitsandbytes/diagnostics/main.py
bitsandbytes/diagnostics/utils.py
bitsandbytes/nn/__init__.py
bitsandbytes/nn/modules.py
bitsandbytes/nn/triton_based_modules.py
bitsandbytes/optim/__init__.py
bitsandbytes/optim/adagrad.py
bitsandbytes/optim/adam.py
bitsandbytes/optim/adamw.py
bitsandbytes/optim/lamb.py
bitsandbytes/optim/lars.py
bitsandbytes/optim/lion.py
bitsandbytes/optim/optimizer.py
bitsandbytes/optim/rmsprop.py
bitsandbytes/optim/sgd.py
bitsandbytes/research/__init__.py
bitsandbytes/research/autograd/__init__.py
bitsandbytes/research/autograd/_functions.py
bitsandbytes/research/nn/__init__.py
bitsandbytes/research/nn/modules.py
bitsandbytes/triton/__init__.py
bitsandbytes/triton/dequantize_rowwise.py
bitsandbytes/triton/int8_matmul_mixed_dequantize.py
bitsandbytes/triton/int8_matmul_rowwise_dequantize.py
bitsandbytes/triton/quantize_columnwise_and_transpose.py
bitsandbytes/triton/quantize_global.py
bitsandbytes/triton/quantize_rowwise.py
bitsandbytes/triton/triton_utils.py
tests/__init__.py
tests/conftest.py
tests/helpers.py
tests/test_autograd.py
tests/test_cuda_setup_evaluator.py
tests/test_functional.py
tests/test_generation.py
tests/test_linear4bit.py
tests/test_linear8bitlt.py
tests/test_modules.py
tests/test_optim.py
tests/test_triton.py
bitsandbytes_npu_beta-0.45.3.dist-info/LICENSE
bitsandbytes_npu_beta-0.45.3.dist-info/METADATA
bitsandbytes_npu_beta-0.45.3.dist-info/NOTICE.md
bitsandbytes_npu_beta-0.45.3.dist-info/WHEEL
bitsandbytes_npu_beta-0.45.3.dist-info/top_level.txt
bitsandbytes_npu_beta-0.45.3.dist-info/RECORD
